pyBamParser/__init__.py
pyBamParser/bai/__init__.py
pyBamParser/bam/__init__.py
pyBamParser/bgzf/__init__.py
pyBamParser/fasta/__init__.py
pyBamParser/read/__init__.py
pyBamParser/util/__init__.py
pyBamParser/util/odict.py
pyBamParser/util/packer.py
pyBamParser-0.0.3.dist-info/DESCRIPTION.rst
pyBamParser-0.0.3.dist-info/METADATA
pyBamParser-0.0.3.dist-info/RECORD
pyBamParser-0.0.3.dist-info/WHEEL
pyBamParser-0.0.3.dist-info/metadata.json
pyBamParser-0.0.3.dist-info/top_level.txt
