Metadata-Version: 2.0
Name: pyBamParser
Version: 0.0.3
Summary: Tools for parsing BAM data
Home-page: https://github.com/blankenberg/pyBamParser
Author: Daniel Blankenberg
Author-email: dan.blankenberg@gmail.com
License: GPLv2
Platform: UNKNOWN
Classifier: Development Status :: 4 - Beta
Classifier: License :: OSI Approved :: GNU General Public License v2 (GPLv2)
